README.md
easytimeout.py
setup.py
easytimeout.egg-info/PKG-INFO
easytimeout.egg-info/SOURCES.txt
easytimeout.egg-info/dependency_links.txt
easytimeout.egg-info/top_level.txt