Metadata-Version: 1.0
Name: easytimeout
Version: 0.0.2
Summary: Add time limit to excution of your function
Home-page: https://github.com/binzaq/easytimeout.git
Author: bizq
Author-email: bin.zaq@foxmail.com
License: Apache Licence
Keywords: timeout,easytimeout
Platform: any
